tacker/__init__.py
tacker/_i18n.py
tacker/auth.py
tacker/context.py
tacker/manager.py
tacker/policy.py
tacker/service.py
tacker/version.py
tacker/wsgi.py
tacker/agent/__init__.py
tacker/agent/linux/__init__.py
tacker/agent/linux/utils.py
tacker/api/__init__.py
tacker/api/api_common.py
tacker/api/extensions.py
tacker/api/versions.py
tacker/api/common/__init__.py
tacker/api/common/_filters.py
tacker/api/common/attribute_filter.py
tacker/api/schemas/__init__.py
tacker/api/schemas/vnf_lcm.py
tacker/api/schemas/vnf_packages.py
tacker/api/v1/__init__.py
tacker/api/v1/attributes.py
tacker/api/v1/base.py
tacker/api/v1/resource.py
tacker/api/v1/resource_helper.py
tacker/api/v1/router.py
tacker/api/validation/__init__.py
tacker/api/validation/parameter_types.py
tacker/api/validation/validators.py
tacker/api/views/__init__.py
tacker/api/views/versions.py
tacker/api/views/vnf_lcm.py
tacker/api/views/vnf_lcm_op_occs.py
tacker/api/views/vnf_packages.py
tacker/api/views/vnf_subscriptions.py
tacker/api/vnflcm/__init__.py
tacker/api/vnflcm/v1/__init__.py
tacker/api/vnflcm/v1/controller.py
tacker/api/vnflcm/v1/router.py
tacker/api/vnflcm/v1/sync_resource.py
tacker/api/vnfpkgm/__init__.py
tacker/api/vnfpkgm/v1/__init__.py
tacker/api/vnfpkgm/v1/controller.py
tacker/api/vnfpkgm/v1/router.py
tacker/cmd/__init__.py
tacker/cmd/status.py
tacker/cmd/eventlet/__init__.py
tacker/cmd/eventlet/conductor.py
tacker/cmd/eventlet/tacker_server.py
tacker/common/__init__.py
tacker/common/clients.py
tacker/common/cmd_executer.py
tacker/common/config.py
tacker/common/constants.py
tacker/common/coordination.py
tacker/common/crypt_utils.py
tacker/common/csar_utils.py
tacker/common/driver_manager.py
tacker/common/eventlet_utils.py
tacker/common/exceptions.py
tacker/common/ext_oauth2_auth.py
tacker/common/log.py
tacker/common/oidc_utils.py
tacker/common/rpc.py
tacker/common/safe_utils.py
tacker/common/test_lib.py
tacker/common/topics.py
tacker/common/utils.py
tacker/common/container/__init__.py
tacker-14.0.0.dist-info/AUTHORS
tacker-14.0.0.dist-info/LICENSE
tacker-14.0.0.dist-info/METADATA
tacker-14.0.0.dist-info/WHEEL
tacker-14.0.0.dist-info/entry_points.txt
tacker-14.0.0.dist-info/pbr.json
tacker-14.0.0.dist-info/top_level.txt
tacker-14.0.0.dist-info/RECORD
