Metadata-Version: 2.1
Name: tacker
Version: 14.0.0
Summary: OpenStack NFV Orchestration
Home-page: https://docs.openstack.org/tacker/
Author: OpenStack
Author-email: openstack-discuss@lists.openstack.org
Classifier: Environment :: OpenStack
Classifier: Intended Audience :: Information Technology
Classifier: Intended Audience :: System Administrators
Classifier: License :: OSI Approved :: Apache Software License
Classifier: Operating System :: POSIX :: Linux
Classifier: Programming Language :: Python
Classifier: Programming Language :: Python :: 3
Classifier: Programming Language :: Python :: 3.10
Classifier: Programming Language :: Python :: 3.11
Classifier: Programming Language :: Python :: 3.12
Requires-Python: >=3.10
License-File: LICENSE
License-File: AUTHORS
Requires-Dist: pbr >=5.5.0
Requires-Dist: Paste >=2.0.2
Requires-Dist: PasteDeploy >=1.5.0
Requires-Dist: Routes >=2.3.1
Requires-Dist: amqp >=2.4.0
Requires-Dist: eventlet >=0.30.1
Requires-Dist: requests >=2.25.1
Requires-Dist: jsonschema >=3.2.0
Requires-Dist: keystonemiddleware >=4.17.0
Requires-Dist: kombu >=4.3.0
Requires-Dist: netaddr >=0.7.18
Requires-Dist: SQLAlchemy >=1.3.11
Requires-Dist: WebOb >=1.7.1
Requires-Dist: alembic >=0.9.6
Requires-Dist: stevedore >=3.3.0
Requires-Dist: oslo.concurrency >=3.26.0
Requires-Dist: oslo.config >=6.8.0
Requires-Dist: oslo.context >=2.22.0
Requires-Dist: oslo.db >=5.0.0
Requires-Dist: oslo.log >=3.36.0
Requires-Dist: oslo.messaging >=14.2.0
Requires-Dist: oslo.middleware >=3.31.0
Requires-Dist: oslo.policy >=4.5.0
Requires-Dist: oslo.reports >=1.18.0
Requires-Dist: oslo.serialization !=2.19.1,>=2.18.0
Requires-Dist: oslo.service >=2.5.0
Requires-Dist: oslo.upgradecheck >=1.3.0
Requires-Dist: oslo.utils >=7.0.0
Requires-Dist: oslo.versionedobjects >=1.33.3
Requires-Dist: openstacksdk >=0.44.0
Requires-Dist: python-barbicanclient >=4.5.2
Requires-Dist: python-heatclient >=1.10.0
Requires-Dist: python-keystoneclient >=3.8.0
Requires-Dist: python-neutronclient >=6.7.0
Requires-Dist: python-novaclient >=9.1.0
Requires-Dist: python-tackerclient >=1.11.0
Requires-Dist: rfc3986 >=1.2.0
Requires-Dist: cryptography >=2.7
Requires-Dist: paramiko >=2.7.1
Requires-Dist: castellan >=0.16.0
Requires-Dist: kubernetes >=18.20.0
Requires-Dist: setuptools !=24.0.0,!=34.0.0,!=34.0.1,!=34.0.2,!=34.0.3,!=34.1.0,!=34.1.1,!=34.2.0,!=34.3.0,!=34.3.1,!=34.3.2,!=36.2.0,>=21.0.0
Requires-Dist: tooz >=1.58.0
Requires-Dist: PyYAML >=5.4.1
Requires-Dist: PyMySQL >=0.10.1
Requires-Dist: PyJWT >=2.4.0
Requires-Dist: glance-store >=2.4.0
Requires-Dist: heat-translator >=2.3.0
Requires-Dist: tosca-parser >=2.3.0
Requires-Dist: pyroute2 >=0.4.21 ; (sys_platform!='win32')
